<?xml version="1.0" encoding="UTF-8"?>
<MetaDataObject xmlns="http://v8.1c.ru/8.3/MDClasses" xmlns:app="http://v8.1c.ru/8.2/managed-application/core" xmlns:cfg="http://v8.1c.ru/8.1/data/enterprise/current-config" xmlns:cmi="http://v8.1c.ru/8.2/managed-application/cmi" xmlns:ent="http://v8.1c.ru/8.1/data/enterprise" xmlns:lf="http://v8.1c.ru/8.2/managed-application/logform" xmlns:style="http://v8.1c.ru/8.1/data/ui/style" xmlns:sys="http://v8.1c.ru/8.1/data/ui/fonts/system" xmlns:v8="http://v8.1c.ru/8.1/data/core" xmlns:v8ui="http://v8.1c.ru/8.1/data/ui" xmlns:web="http://v8.1c.ru/8.1/data/ui/colors/web" xmlns:win="http://v8.1c.ru/8.1/data/ui/colors/windows" xmlns:xen="http://v8.1c.ru/8.3/xcf/enums" xmlns:xpr="http://v8.1c.ru/8.3/xcf/predef" xmlns:xr="http://v8.1c.ru/8.3/xcf/readable" xmlns:xs="http://www.w3.org/2001/XMLSchema" xmlns:xsi="http://www.w3.org/2001/XMLSchema-instance" version="2.11">
	<DocumentJournal uuid="dcdaa5b5-00fd-40e7-889f-35051b2603c0">
		<InternalInfo>
			<xr:GeneratedType name="DocumentJournalSelection.СкладскиеДокументы" category="Selection">
				<xr:TypeId>9b6552e5-caa9-47e2-8c9b-f24fd2817886</xr:TypeId>
				<xr:ValueId>0a90491d-2ae1-4551-863b-1e236f6e0e81</xr:ValueId>
			</xr:GeneratedType>
			<xr:GeneratedType name="DocumentJournalList.СкладскиеДокументы" category="List">
				<xr:TypeId>565bef68-0da2-46c8-a83b-853e30dfe769</xr:TypeId>
				<xr:ValueId>31f622c7-f7d1-4d09-9454-f1bff3f46bee</xr:ValueId>
			</xr:GeneratedType>
			<xr:GeneratedType name="DocumentJournalManager.СкладскиеДокументы" category="Manager">
				<xr:TypeId>f513fa85-af7e-44dc-a5d0-2e286d204b42</xr:TypeId>
				<xr:ValueId>f37862ed-8de0-4d48-91c1-aa64d2fb5da2</xr:ValueId>
			</xr:GeneratedType>
		</InternalInfo>
		<Properties>
			<Name>СкладскиеДокументы</Name>
			<Synonym>
				<v8:item>
					<v8:lang>ru</v8:lang>
					<v8:content>Складские документы</v8:content>
				</v8:item>
			</Synonym>
			<Comment/>
			<DefaultForm>DocumentJournal.СкладскиеДокументы.Form.ФормаСписка</DefaultForm>
			<AuxiliaryForm/>
			<UseStandardCommands>true</UseStandardCommands>
			<RegisteredDocuments>
				<xr:Item xsi:type="xr:MDObjectRef">Document.Инвентаризация</xr:Item>
				<xr:Item xsi:type="xr:MDObjectRef">Document.Поступление</xr:Item>
				<xr:Item xsi:type="xr:MDObjectRef">Document.Перемещение</xr:Item>
				<xr:Item xsi:type="xr:MDObjectRef">Document.СборкаКомплектация</xr:Item>
				<xr:Item xsi:type="xr:MDObjectRef">Document.РазбиениеКомплектации</xr:Item>
				<xr:Item xsi:type="xr:MDObjectRef">Document.Списание</xr:Item>
			</RegisteredDocuments>
			<IncludeHelpInContents>false</IncludeHelpInContents>
			<StandardAttributes>
				<xr:StandardAttribute name="Type">
					<xr:LinkByType/>
					<xr:FillChecking>DontCheck</xr:FillChecking>
					<xr:MultiLine>false</xr:MultiLine>
					<xr:FillFromFillingValue>false</xr:FillFromFillingValue>
					<xr:CreateOnInput>Auto</xr:CreateOnInput>
					<xr:MaxValue xsi:nil="true"/>
					<xr:ToolTip/>
					<xr:ExtendedEdit>false</xr:ExtendedEdit>
					<xr:Format/>
					<xr:ChoiceForm/>
					<xr:QuickChoice>Auto</xr:QuickChoice>
					<xr:ChoiceHistoryOnInput>Auto</xr:ChoiceHistoryOnInput>
					<xr:EditFormat/>
					<xr:PasswordMode>false</xr:PasswordMode>
					<xr:DataHistory>Use</xr:DataHistory>
					<xr:MarkNegatives>false</xr:MarkNegatives>
					<xr:MinValue xsi:nil="true"/>
					<xr:Synonym/>
					<xr:Comment/>
					<xr:FullTextSearch>Use</xr:FullTextSearch>
					<xr:ChoiceParameterLinks/>
					<xr:FillValue xsi:nil="true"/>
					<xr:Mask/>
					<xr:ChoiceParameters/>
				</xr:StandardAttribute>
				<xr:StandardAttribute name="Ref">
					<xr:LinkByType/>
					<xr:FillChecking>DontCheck</xr:FillChecking>
					<xr:MultiLine>false</xr:MultiLine>
					<xr:FillFromFillingValue>false</xr:FillFromFillingValue>
					<xr:CreateOnInput>Auto</xr:CreateOnInput>
					<xr:MaxValue xsi:nil="true"/>
					<xr:ToolTip/>
					<xr:ExtendedEdit>false</xr:ExtendedEdit>
					<xr:Format/>
					<xr:ChoiceForm/>
					<xr:QuickChoice>Auto</xr:QuickChoice>
					<xr:ChoiceHistoryOnInput>Auto</xr:ChoiceHistoryOnInput>
					<xr:EditFormat/>
					<xr:PasswordMode>false</xr:PasswordMode>
					<xr:DataHistory>Use</xr:DataHistory>
					<xr:MarkNegatives>false</xr:MarkNegatives>
					<xr:MinValue xsi:nil="true"/>
					<xr:Synonym/>
					<xr:Comment/>
					<xr:FullTextSearch>Use</xr:FullTextSearch>
					<xr:ChoiceParameterLinks/>
					<xr:FillValue xsi:nil="true"/>
					<xr:Mask/>
					<xr:ChoiceParameters/>
				</xr:StandardAttribute>
				<xr:StandardAttribute name="Date">
					<xr:LinkByType/>
					<xr:FillChecking>DontCheck</xr:FillChecking>
					<xr:MultiLine>false</xr:MultiLine>
					<xr:FillFromFillingValue>false</xr:FillFromFillingValue>
					<xr:CreateOnInput>Auto</xr:CreateOnInput>
					<xr:MaxValue xsi:nil="true"/>
					<xr:ToolTip/>
					<xr:ExtendedEdit>false</xr:ExtendedEdit>
					<xr:Format/>
					<xr:ChoiceForm/>
					<xr:QuickChoice>Auto</xr:QuickChoice>
					<xr:ChoiceHistoryOnInput>Auto</xr:ChoiceHistoryOnInput>
					<xr:EditFormat/>
					<xr:PasswordMode>false</xr:PasswordMode>
					<xr:DataHistory>Use</xr:DataHistory>
					<xr:MarkNegatives>false</xr:MarkNegatives>
					<xr:MinValue xsi:nil="true"/>
					<xr:Synonym/>
					<xr:Comment/>
					<xr:FullTextSearch>Use</xr:FullTextSearch>
					<xr:ChoiceParameterLinks/>
					<xr:FillValue xsi:nil="true"/>
					<xr:Mask/>
					<xr:ChoiceParameters/>
				</xr:StandardAttribute>
				<xr:StandardAttribute name="Posted">
					<xr:LinkByType/>
					<xr:FillChecking>DontCheck</xr:FillChecking>
					<xr:MultiLine>false</xr:MultiLine>
					<xr:FillFromFillingValue>false</xr:FillFromFillingValue>
					<xr:CreateOnInput>Auto</xr:CreateOnInput>
					<xr:MaxValue xsi:nil="true"/>
					<xr:ToolTip/>
					<xr:ExtendedEdit>false</xr:ExtendedEdit>
					<xr:Format/>
					<xr:ChoiceForm/>
					<xr:QuickChoice>Auto</xr:QuickChoice>
					<xr:ChoiceHistoryOnInput>Auto</xr:ChoiceHistoryOnInput>
					<xr:EditFormat/>
					<xr:PasswordMode>false</xr:PasswordMode>
					<xr:DataHistory>Use</xr:DataHistory>
					<xr:MarkNegatives>false</xr:MarkNegatives>
					<xr:MinValue xsi:nil="true"/>
					<xr:Synonym/>
					<xr:Comment/>
					<xr:FullTextSearch>Use</xr:FullTextSearch>
					<xr:ChoiceParameterLinks/>
					<xr:FillValue xsi:nil="true"/>
					<xr:Mask/>
					<xr:ChoiceParameters/>
				</xr:StandardAttribute>
				<xr:StandardAttribute name="DeletionMark">
					<xr:LinkByType/>
					<xr:FillChecking>DontCheck</xr:FillChecking>
					<xr:MultiLine>false</xr:MultiLine>
					<xr:FillFromFillingValue>false</xr:FillFromFillingValue>
					<xr:CreateOnInput>Auto</xr:CreateOnInput>
					<xr:MaxValue xsi:nil="true"/>
					<xr:ToolTip/>
					<xr:ExtendedEdit>false</xr:ExtendedEdit>
					<xr:Format/>
					<xr:ChoiceForm/>
					<xr:QuickChoice>Auto</xr:QuickChoice>
					<xr:ChoiceHistoryOnInput>Auto</xr:ChoiceHistoryOnInput>
					<xr:EditFormat/>
					<xr:PasswordMode>false</xr:PasswordMode>
					<xr:DataHistory>Use</xr:DataHistory>
					<xr:MarkNegatives>false</xr:MarkNegatives>
					<xr:MinValue xsi:nil="true"/>
					<xr:Synonym/>
					<xr:Comment/>
					<xr:FullTextSearch>Use</xr:FullTextSearch>
					<xr:ChoiceParameterLinks/>
					<xr:FillValue xsi:nil="true"/>
					<xr:Mask/>
					<xr:ChoiceParameters/>
				</xr:StandardAttribute>
				<xr:StandardAttribute name="Number">
					<xr:LinkByType/>
					<xr:FillChecking>DontCheck</xr:FillChecking>
					<xr:MultiLine>false</xr:MultiLine>
					<xr:FillFromFillingValue>false</xr:FillFromFillingValue>
					<xr:CreateOnInput>Auto</xr:CreateOnInput>
					<xr:MaxValue xsi:nil="true"/>
					<xr:ToolTip/>
					<xr:ExtendedEdit>false</xr:ExtendedEdit>
					<xr:Format/>
					<xr:ChoiceForm/>
					<xr:QuickChoice>Auto</xr:QuickChoice>
					<xr:ChoiceHistoryOnInput>Auto</xr:ChoiceHistoryOnInput>
					<xr:EditFormat/>
					<xr:PasswordMode>false</xr:PasswordMode>
					<xr:DataHistory>Use</xr:DataHistory>
					<xr:MarkNegatives>false</xr:MarkNegatives>
					<xr:MinValue xsi:nil="true"/>
					<xr:Synonym/>
					<xr:Comment/>
					<xr:FullTextSearch>Use</xr:FullTextSearch>
					<xr:ChoiceParameterLinks/>
					<xr:FillValue xsi:nil="true"/>
					<xr:Mask/>
					<xr:ChoiceParameters/>
				</xr:StandardAttribute>
			</StandardAttributes>
			<ListPresentation/>
			<ExtendedListPresentation/>
			<Explanation>
				<v8:item>
					<v8:lang>ru</v8:lang>
					<v8:content>Все документы по которым происходят складские операции</v8:content>
				</v8:item>
			</Explanation>
		</Properties>
		<ChildObjects>
			<Column uuid="c51e5047-4fd4-4442-84fd-601fb3e4cd64">
				<Properties>
					<Name>Организация</Name>
					<Synonym>
						<v8:item>
							<v8:lang>ru</v8:lang>
							<v8:content>Организация</v8:content>
						</v8:item>
					</Synonym>
					<Comment/>
					<Indexing>DontIndex</Indexing>
					<References>
						<xr:Item xsi:type="xr:MDObjectRef">Document.Поступление.Attribute.Организация</xr:Item>
						<xr:Item xsi:type="xr:MDObjectRef">Document.Перемещение.Attribute.ОрганизацияРасхода</xr:Item>
						<xr:Item xsi:type="xr:MDObjectRef">Document.Списание.Attribute.Организация</xr:Item>
						<xr:Item xsi:type="xr:MDObjectRef">Document.СборкаКомплектация.Attribute.Организация</xr:Item>
						<xr:Item xsi:type="xr:MDObjectRef">Document.РазбиениеКомплектации.Attribute.Организация</xr:Item>
						<xr:Item xsi:type="xr:MDObjectRef">Document.Инвентаризация.Attribute.Организация</xr:Item>
					</References>
				</Properties>
			</Column>
			<Column uuid="9a4d868d-3513-4f56-9553-324fa79f6355">
				<Properties>
					<Name>Подразделение</Name>
					<Synonym>
						<v8:item>
							<v8:lang>ru</v8:lang>
							<v8:content>Подразделение</v8:content>
						</v8:item>
					</Synonym>
					<Comment/>
					<Indexing>DontIndex</Indexing>
					<References>
						<xr:Item xsi:type="xr:MDObjectRef">Document.Инвентаризация.Attribute.Подразделение</xr:Item>
						<xr:Item xsi:type="xr:MDObjectRef">Document.Перемещение.Attribute.Подразделение</xr:Item>
						<xr:Item xsi:type="xr:MDObjectRef">Document.Поступление.Attribute.Подразделение</xr:Item>
						<xr:Item xsi:type="xr:MDObjectRef">Document.РазбиениеКомплектации.Attribute.Подразделение</xr:Item>
						<xr:Item xsi:type="xr:MDObjectRef">Document.СборкаКомплектация.Attribute.Подразделение</xr:Item>
						<xr:Item xsi:type="xr:MDObjectRef">Document.Списание.Attribute.Подразделение</xr:Item>
					</References>
				</Properties>
			</Column>
			<Column uuid="afd7e909-7c21-4fa6-ae42-b3a4cdf07125">
				<Properties>
					<Name>МестоХранения</Name>
					<Synonym>
						<v8:item>
							<v8:lang>ru</v8:lang>
							<v8:content>Место хранения</v8:content>
						</v8:item>
					</Synonym>
					<Comment/>
					<Indexing>DontIndex</Indexing>
					<References>
						<xr:Item xsi:type="xr:MDObjectRef">Document.Поступление.Attribute.МестоХранения</xr:Item>
						<xr:Item xsi:type="xr:MDObjectRef">Document.Перемещение.Attribute.МестоХраненияРасхода</xr:Item>
						<xr:Item xsi:type="xr:MDObjectRef">Document.Списание.Attribute.МестоХранения</xr:Item>
						<xr:Item xsi:type="xr:MDObjectRef">Document.СборкаКомплектация.Attribute.МестоХранения</xr:Item>
						<xr:Item xsi:type="xr:MDObjectRef">Document.РазбиениеКомплектации.Attribute.МестоХранения</xr:Item>
						<xr:Item xsi:type="xr:MDObjectRef">Document.Инвентаризация.Attribute.МестоХранения</xr:Item>
					</References>
				</Properties>
			</Column>
			<Column uuid="5a9b87c8-6663-4478-86af-329f1a683a00">
				<Properties>
					<Name>Автор</Name>
					<Synonym>
						<v8:item>
							<v8:lang>ru</v8:lang>
							<v8:content>Автор</v8:content>
						</v8:item>
					</Synonym>
					<Comment/>
					<Indexing>DontIndex</Indexing>
					<References>
						<xr:Item xsi:type="xr:MDObjectRef">Document.Поступление.Attribute.Автор</xr:Item>
						<xr:Item xsi:type="xr:MDObjectRef">Document.Перемещение.Attribute.Автор</xr:Item>
						<xr:Item xsi:type="xr:MDObjectRef">Document.Списание.Attribute.Автор</xr:Item>
						<xr:Item xsi:type="xr:MDObjectRef">Document.СборкаКомплектация.Attribute.Автор</xr:Item>
						<xr:Item xsi:type="xr:MDObjectRef">Document.РазбиениеКомплектации.Attribute.Автор</xr:Item>
						<xr:Item xsi:type="xr:MDObjectRef">Document.Инвентаризация.Attribute.Автор</xr:Item>
					</References>
				</Properties>
			</Column>
			<Column uuid="60f3740d-d1be-4fa2-9c59-407533c837ec">
				<Properties>
					<Name>Комментарий</Name>
					<Synonym>
						<v8:item>
							<v8:lang>ru</v8:lang>
							<v8:content>Комментарий</v8:content>
						</v8:item>
					</Synonym>
					<Comment/>
					<Indexing>DontIndex</Indexing>
					<References>
						<xr:Item xsi:type="xr:MDObjectRef">Document.Поступление.Attribute.Комментарий</xr:Item>
						<xr:Item xsi:type="xr:MDObjectRef">Document.Перемещение.Attribute.Комментарий</xr:Item>
						<xr:Item xsi:type="xr:MDObjectRef">Document.Списание.Attribute.Комментарий</xr:Item>
						<xr:Item xsi:type="xr:MDObjectRef">Document.СборкаКомплектация.Attribute.Комментарий</xr:Item>
						<xr:Item xsi:type="xr:MDObjectRef">Document.РазбиениеКомплектации.Attribute.Комментарий</xr:Item>
						<xr:Item xsi:type="xr:MDObjectRef">Document.Инвентаризация.Attribute.Комментарий</xr:Item>
					</References>
				</Properties>
			</Column>
			<Form>ФормаСписка</Form>
		</ChildObjects>
	</DocumentJournal>
</MetaDataObject>